ready/__init__.py
ready/__version__.py
ready/py.typed
ready/ready.py
ready-0.5.2.dist-info/LICENSE
ready-0.5.2.dist-info/WHEEL
ready-0.5.2.dist-info/METADATA
ready-0.5.2.dist-info/RECORD
