Metadata-Version: 2.1
Name: ready
Version: 0.5.2
Summary: Take control of the event loop with simplified task management and queueing
Home-page: https://github.com/kalaspuff/ready
License: MIT
Keywords: ready
Author: Carl Oscar Aaro
Author-email: hello@carloscar.com
Requires-Python: >=3.6,<4.0
Classifier: Development Status :: 1 - Planning
Classifier: Framework :: AsyncIO
Classifier: Intended Audience :: Developers
Classifier: License :: OSI Approved :: MIT License
Classifier: Programming Language :: Python
Classifier: Programming Language :: Python :: 3
Classifier: Programming Language :: Python :: 3.6
Classifier: Programming Language :: Python :: 3.7
Classifier: Programming Language :: Python :: 3.8
Classifier: Topic :: Software Development
Classifier: Topic :: Software Development :: Libraries
Classifier: Typing :: Typed
Project-URL: Repository, https://github.com/kalaspuff/ready
